fletch/__init__.py
fletch/fletch.py
fletch_lib-0.1.1.dist-info/METADATA
fletch_lib-0.1.1.dist-info/WHEEL
fletch_lib-0.1.1.dist-info/top_level.txt
fletch_lib-0.1.1.dist-info/RECORD
