Metadata-Version: 2.4
Name: fletch_lib
Version: 0.1.1
Summary: A simple utility package for personal use.
Home-page: https://github.com/fbsmith/fletch
Author: Fletcher Smith
Author-email: fletcherbsmith@gmail.com
Classifier: Programming Language :: Python :: 3
Classifier: License :: OSI Approved :: MIT License
Classifier: Operating System :: OS Independent
Requires-Python: >=3.11
Dynamic: author
Dynamic: author-email
Dynamic: classifier
Dynamic: description-content-type
Dynamic: home-page
Dynamic: requires-python
Dynamic: summary
